[
  {
    "_id": "637c0b6b24f9fcbd16030756",
    "index": 0,
    "guid": "c7a0fc1e-e744-4d8e-ba55-64f77c261df6",
    "isActive": false,
    "balance": "$1,012.83",
    "picture": "http://placehold.it/32x32",
    "age": 28,
    "eyeColor": "blue",
    "name": "Eva Floyd",
    "gender": "female",
    "company": "OZEAN",
    "email": "evafloyd@ozean.com",
    "phone": "+1 (913) 500-3481",
    "address": "104 Wythe Place, Helen, Wyoming, 5604",
    "about": "Ipsum quis eu commodo esse tempor sit deserunt irure irure consequat proident enim exercitation amet. Dolore id et cillum velit cillum eu minim tempor amet et ut. Amet culpa in qui Lorem. Minim ad sit do officia aute minim ut excepteur excepteur qui. Ea consectetur laboris quis do sunt ea.\r\n",
    "registered": "2015-07-22T10:42:02 -02:00",
    "latitude": -77.766029,
    "longitude": 43.853286,
    "tags": [
      "sit",
      "consequat",
      "reprehenderit",
      "esse",
      "nulla",
      "ipsum",
      "ad"
    ],
    "friends": [
      {
        "id": 0,
        "name": "Catherine Obrien"
      },
      {
        "id": 1,
        "name": "Eaton Beasley"
      },
      {
        "id": 2,
        "name": "Yvonne Meyer"
      }
    ],
    "greeting": "Hello, Eva Floyd! You have 8 unread messages.",
    "favoriteFruit": "apple"
  },
  {
    "_id": "637c0b6bcd4555772d7c0da0",
    "index": 1,
    "guid": "7414adab-d6ca-4342-91dc-5e0fb03b9bc7",
    "isActive": false,
    "balance": "$3,261.75",
    "picture": "http://placehold.it/32x32",
    "age": 29,
    "eyeColor": "green",
    "name": "Baird Guzman",
    "gender": "male",
    "company": "ANIMALIA",
    "email": "bairdguzman@animalia.com",
    "phone": "+1 (923) 508-2527",
    "address": "537 Columbus Place, Wacissa, Montana, 1990",
    "about": "Id aute labore cupidatat et. Eiusmod ad velit laborum Lorem minim consectetur occaecat in aute duis aliquip irure incididunt dolore. In dolore est aute non ullamco enim irure. Lorem sint irure id qui sint nostrud est reprehenderit eu est quis duis commodo cillum. Aliquip esse veniam mollit aute nisi ea nisi ex culpa proident cillum non consectetur deserunt. Ipsum quis officia cupidatat culpa eiusmod esse id aute id laborum eiusmod deserunt. Dolore tempor velit enim Lorem magna.\r\n",
    "registered": "2016-02-20T01:56:48 -01:00",
    "latitude": 57.928597,
    "longitude": 162.291933,
    "tags": [
      "minim",
      "id",
      "dolor",
      "reprehenderit",
      "minim",
      "officia",
      "magna"
    ],
    "friends": [
      {
        "id": 0,
        "name": "Golden Moore"
      },
      {
        "id": 1,
        "name": "Campos Gates"
      },
      {
        "id": 2,
        "name": "Carole Norman"
      }
    ],
    "greeting": "Hello, Baird Guzman! You have 2 unread messages.",
    "favoriteFruit": "apple"
  },
  {
    "_id": "637c0b6bc824e91e6ff773dc",
    "index": 2,
    "guid": "e72cb2bb-0048-4b8d-b273-b0d6b6364aff",
    "isActive": false,
    "balance": "$2,605.75",
    "picture": "http://placehold.it/32x32",
    "age": 22,
    "eyeColor": "green",
    "name": "Case Dean",
    "gender": "male",
    "company": "FUELWORKS",
    "email": "casedean@fuelworks.com",
    "phone": "+1 (850) 527-3005",
    "address": "425 Huron Street, Stockdale, Indiana, 8994",
    "about": "Sunt aute ipsum sit elit aute veniam ad ut nulla nisi nostrud. Exercitation dolore aliquip tempor nostrud proident laboris. Excepteur labore nostrud excepteur et cillum sint. Cillum quis id esse et deserunt sint. Sit velit sunt sit ea id cupidatat tempor non exercitation sint ipsum.\r\n",
    "registered": "2020-05-23T07:34:19 -02:00",
    "latitude": 12.639312,
    "longitude": -149.663006,
    "tags": [
      "veniam",
      "est",
      "laborum",
      "labore",
      "est",
      "esse",
      "proident"
    ],
    "friends": [
      {
        "id": 0,
        "name": "Hartman Browning"
      },
      {
        "id": 1,
        "name": "Carlene Klein"
      },
      {
        "id": 2,
        "name": "Ophelia Pennington"
      }
    ],
    "greeting": "Hello, Case Dean! You have 10 unread messages.",
    "favoriteFruit": "strawberry"
  },
  {
    "_id": "637c0b6ba4baa2d4217a407e",
    "index": 3,
    "guid": "6ddc77b6-3b04-4352-9205-fa46978f4928",
    "isActive": false,
    "balance": "$1,851.87",
    "picture": "http://placehold.it/32x32",
    "age": 22,
    "eyeColor": "blue",
    "name": "Jamie Valentine",
    "gender": "female",
    "company": "SEALOUD",
    "email": "jamievalentine@sealoud.com",
    "phone": "+1 (959) 535-3624",
    "address": "330 Montague Street, Taycheedah, Massachusetts, 1741",
    "about": "Eu occaecat mollit ullamco sit consequat. Et labore exercitation enim minim do magna nulla eu mollit ad culpa Lorem cupidatat nisi. Dolor velit proident reprehenderit exercitation voluptate.\r\n",
    "registered": "2018-06-06T12:03:42 -02:00",
    "latitude": -16.388171,
    "longitude": 12.324884,
    "tags": [
      "ut",
      "fugiat",
      "exercitation",
      "et",
      "ut",
      "proident",
      "proident"
    ],
    "friends": [
      {
        "id": 0,
        "name": "Chaney Workman"
      },
      {
        "id": 1,
        "name": "Kris Rosario"
      },
      {
        "id": 2,
        "name": "Kinney Ochoa"
      }
    ],
    "greeting": "Hello, Jamie Valentine! You have 5 unread messages.",
    "favoriteFruit": "banana"
  },
  {
    "_id": "637c0b6b5e0e79f2b0e872a1",
    "index": 4,
    "guid": "30cf812a-f9f8-476b-a445-768840dfce1d",
    "isActive": false,
    "balance": "$1,048.01",
    "picture": "http://placehold.it/32x32",
    "age": 22,
    "eyeColor": "brown",
    "name": "Tyson Potts",
    "gender": "male",
    "company": "PIVITOL",
    "email": "tysonpotts@pivitol.com",
    "phone": "+1 (827) 563-3358",
    "address": "439 Loring Avenue, Williams, Colorado, 960",
    "about": "Laborum nisi aute nisi esse dolore ad. Ex aliqua occaecat minim dolor do amet ut aliqua minim labore id dolor amet. Et consectetur ut veniam voluptate occaecat laboris. Cillum cupidatat ullamco sit laborum proident eu voluptate pariatur et cupidatat fugiat excepteur.\r\n",
    "registered": "2021-06-09T08:27:00 -02:00",
    "latitude": -70.491764,
    "longitude": -113.353077,
    "tags": [
      "eiusmod",
      "eiusmod",
      "id",
      "magna",
      "laboris",
      "reprehenderit",
      "veniam"
    ],
    "friends": [
      {
        "id": 0,
        "name": "Aline Weaver"
      },
      {
        "id": 1,
        "name": "Genevieve Kline"
      },
      {
        "id": 2,
        "name": "Barr Hood"
      }
    ],
    "greeting": "Hello, Tyson Potts! You have 10 unread messages.",
    "favoriteFruit": "strawberry"
  },
  {
    "_id": "637c0b6b9c8e05fbf1f27fa7",
    "index": 5,
    "guid": "0ced5c0f-7632-42c5-92ba-0d88dd6071a3",
    "isActive": true,
    "balance": "$1,101.37",
    "picture": "http://placehold.it/32x32",
    "age": 21,
    "eyeColor": "blue",
    "name": "Odom Kane",
    "gender": "male",
    "company": "ELITA",
    "email": "odomkane@elita.com",
    "phone": "+1 (887) 498-2521",
    "address": "561 Tudor Terrace, Santel, South Dakota, 3457",
    "about": "Esse cillum et irure occaecat sint dolore magna duis eiusmod est ea. Deserunt anim occaecat ullamco duis ad officia ut officia laboris. Ut laborum sunt nulla nostrud aute ipsum ad culpa. Eiusmod duis Lorem deserunt aliquip aute aute veniam officia sit. Commodo non commodo veniam magna quis. Ut aute esse nostrud ipsum proident mollit ullamco aliqua enim fugiat.\r\n",
    "registered": "2016-12-16T09:41:48 -01:00",
    "latitude": 46.424509,
    "longitude": 141.611214,
    "tags": [
      "anim",
      "tempor",
      "dolore",
      "commodo",
      "enim",
      "do",
      "quis"
    ],
    "friends": [
      {
        "id": 0,
        "name": "Johanna Mcintosh"
      },
      {
        "id": 1,
        "name": "Aguirre Morales"
      },
      {
        "id": 2,
        "name": "Luna Chan"
      }
    ],
    "greeting": "Hello, Odom Kane! You have 6 unread messages.",
    "favoriteFruit": "banana"
  }
]